LICENSE
setup.py
caph1993_pytools.egg-info/PKG-INFO
caph1993_pytools.egg-info/SOURCES.txt
caph1993_pytools.egg-info/dependency_links.txt
caph1993_pytools.egg-info/requires.txt
caph1993_pytools.egg-info/top_level.txt
cp93pytools/__init__.py
cp93pytools/_dict.py
cp93pytools/audio.py
cp93pytools/collections.py
cp93pytools/command_line.py
cp93pytools/diskdict.py
cp93pytools/geometry.py
cp93pytools/interrupt.py
cp93pytools/methodtools.py
cp93pytools/moduletools.py
cp93pytools/process.py
cp93pytools/quickSearch.py
cp93pytools/songs.py
cp93pytools/custom_json/__init__.py
cp93pytools/custom_json/module_1.py
cp93pytools/easySqlite/__init__.py
cp93pytools/easySqlite/database.py
cp93pytools/easySqlite/query.py
cp93pytools/easySqlite/query_body.py
cp93pytools/easySqlite/store.py
cp93pytools/easySqlite/table.py
cp93pytools/easySqlite/types.py
cp93pytools/strings/__init__.py
cp93pytools/strings/quickSearch.py