Metadata-Version: 2.1
Name: caph1993-pytools
Version: 0.4.13
Summary: Python toolbox of Carlos Pinzón
Home-page: https://github.com/caph1993/caph1993-pytools
Author: Carlos Pinzón
Author-email: caph1993@gmail.com
License: MIT
Platform: UNKNOWN
Classifier: Development Status :: 1 - Planning
Classifier: Intended Audience :: Science/Research
Classifier: License :: OSI Approved :: BSD License
Classifier: Operating System :: POSIX :: Linux
Classifier: Programming Language :: Python :: 3
Classifier: Programming Language :: Python :: 3.6
License-File: LICENSE
